<?xml version="1.0" encoding="utf-8"?>
<!DOCTYPE hibernate-mapping PUBLIC "-//Hibernate/Hibernate Mapping DTD 3.0//EN"
"http://hibernate.sourceforge.net/hibernate-mapping-3.0.dtd">
<!-- 
    Mapping file autogenerated by MyEclipse Persistence Tools
-->
<hibernate-mapping>
    <class name="com.pojo.Qinshi" table="qinshi" catalog="bedroom">
        <id name="qinshiId" type="java.lang.Short">
            <column name="qinshi_id" />
            <generator class="native" />
        </id>
        <property name="qinshiCeng" type="java.lang.Integer">
            <column name="qinshi_ceng">
                <comment>寝室的楼层数目</comment>
            </column>
        </property>
        <property name="qinshiAddress" type="java.lang.String">
            <column name="qinshi_address" length="300">
                <comment>寝室地址</comment>
            </column>
        </property>
        <property name="qinshiCengrooms" type="java.lang.String">
            <column name="qinshi_cengrooms" length="100">
                <comment>寝室楼每层的人数 例如26,26,26,26,26</comment>
            </column>
        </property>
        <set name="rooms" inverse="true">
            <key>
                <column name="qinshi_id">
                    <comment>哪一栋的 是个外键</comment>
                </column>
            </key>
            <one-to-many class="com.pojo.Room" />
        </set>
    </class>
</hibernate-mapping>
